MuPythonLibrary/MuAnsiHandler.py
MuPythonLibrary/MuAnsiHandler_test.py
MuPythonLibrary/MuFileHandler.py
MuPythonLibrary/MuJunitReport.py
MuPythonLibrary/MuMarkdownHandler.py
MuPythonLibrary/MuStringHandler.py
MuPythonLibrary/UtilityFunctions.py
MuPythonLibrary/__init__.py
MuPythonLibrary/feature_GetHostInfo.md
MuPythonLibrary/feature_MuAnsiHandler.md
MuPythonLibrary/ACPI/DMARParser.py
MuPythonLibrary/TPM/Tpm2Defs.py
MuPythonLibrary/TPM/Tpm2Defs_Test.py
MuPythonLibrary/TPM/Tpm2PolicyCalc.py
MuPythonLibrary/TPM/Tpm2PolicyCalc_Test.py
MuPythonLibrary/TPM/Tpm2Simulator.py
MuPythonLibrary/TPM/Tpm2Stream.py
MuPythonLibrary/TPM/Tpm2Stream_Test.py
MuPythonLibrary/Uefi/BmpObject.py
MuPythonLibrary/Uefi/BmpObject_test.py
MuPythonLibrary/Uefi/FtwWorkingBlockFormat.py
MuPythonLibrary/Uefi/UefiAuthenticatedVariablesStructureSupport.py
MuPythonLibrary/Uefi/UefiMultiPhase.py
MuPythonLibrary/Uefi/UefiStatusCode.py
MuPythonLibrary/Uefi/VariableStoreManipulation.py
MuPythonLibrary/Uefi/WinCert.py
MuPythonLibrary/Uefi/__init__.py
MuPythonLibrary/Uefi/Capsule/CatGenerator.py
MuPythonLibrary/Uefi/Capsule/CatGenerator_test.py
MuPythonLibrary/Uefi/Capsule/InfGenerator.py
MuPythonLibrary/Uefi/Capsule/InfGenerator_test.py
MuPythonLibrary/Uefi/Capsule/__init__.py
MuPythonLibrary/Uefi/EdkII/PathUtilities.py
MuPythonLibrary/Uefi/EdkII/PiFirmwareFile.py
MuPythonLibrary/Uefi/EdkII/PiFirmwareVolume.py
MuPythonLibrary/Uefi/EdkII/VariableFormat.py
MuPythonLibrary/Uefi/EdkII/VariableFormat_Test.py
MuPythonLibrary/Uefi/EdkII/__init__.py
MuPythonLibrary/Uefi/EdkII/Parsers/BaseParser.py
MuPythonLibrary/Uefi/EdkII/Parsers/BuildReportParser.py
MuPythonLibrary/Uefi/EdkII/Parsers/DecParser.py
MuPythonLibrary/Uefi/EdkII/Parsers/DscParser.py
MuPythonLibrary/Uefi/EdkII/Parsers/FdfParser.py
MuPythonLibrary/Uefi/EdkII/Parsers/InfParser.py
MuPythonLibrary/Uefi/EdkII/Parsers/OverrideParser.py
MuPythonLibrary/Uefi/EdkII/Parsers/OverrideParser_Test.py
MuPythonLibrary/Uefi/EdkII/Parsers/TargetTxtParser.py
mu_python_library-0.4.7.dist-info/LICENSE
mu_python_library-0.4.7.dist-info/METADATA
mu_python_library-0.4.7.dist-info/WHEEL
mu_python_library-0.4.7.dist-info/top_level.txt
mu_python_library-0.4.7.dist-info/RECORD
