Metadata-Version: 2.1
Name: mu-python-library
Version: 0.4.7
Summary: Python library supporting Project Mu components (EDKII, TPM, Capsules, etc.)
Home-page: https://github.com/microsoft/mu_pip_python_library
Author: Project Mu Team
Author-email: maknutse@microsoft.com
License: BSD2
Platform: UNKNOWN
Classifier: Programming Language :: Python :: 3
Classifier: License :: OSI Approved :: BSD License
Classifier: Operating System :: OS Independent
Classifier: Development Status :: 4 - Beta
